regex_llm/__init__.py
regex_llm-0.1.0.dist-info/METADATA
regex_llm-0.1.0.dist-info/WHEEL
regex_llm-0.1.0.dist-info/RECORD
