Metadata-Version: 2.1
Name: regex-llm
Version: 0.1.0
Summary: Controlled language model generation using regex
Home-page: https://github.com/yanyongyu/regex-llm
License: MIT
Keywords: llm,regex,language model,generation
Author: yanyongyu
Author-email: yyy@yyydl.top
Requires-Python: >=3.8,<4.0
Classifier: License :: OSI Approved :: MIT License
Classifier: Programming Language :: Python :: 3
Classifier: Programming Language :: Python :: 3.8
Classifier: Programming Language :: Python :: 3.9
Classifier: Programming Language :: Python :: 3.10
Classifier: Programming Language :: Python :: 3.11
Requires-Dist: regex (>=2023.5.5,<2024.0.0)
Requires-Dist: transformers (>=4.29.2,<5.0.0)
Project-URL: Documentation, https://github.com/yanyongyu/regex-llm
Project-URL: Repository, https://github.com/yanyongyu/regex-llm
